pytoolsx/__init__.py
pytoolsx/pytoools.py
pytoolsx-0.1.0.dist-info/LICENSE
pytoolsx-0.1.0.dist-info/METADATA
pytoolsx-0.1.0.dist-info/WHEEL
pytoolsx-0.1.0.dist-info/top_level.txt
pytoolsx-0.1.0.dist-info/RECORD
