Metadata-Version: 2.2
Name: pytoolsx
Version: 0.1.0
Summary: A simple Python tools library
Author-email: Your Name <your@email.com>
License: MIT License
Project-URL: Homepage, https://github.com/yourusername/pytoolsx
Project-URL: Documentation, https://yourwebsite.com/docs
Requires-Python: >=3.7
License-File: LICENSE
Requires-Dist: requests
